ssm_client-0.5.1.dist-info/METADATA
ssm_client-0.5.1.dist-info/WHEEL
ssm_client-0.5.1.dist-info/licenses/AUTHORS.rst
ssm_client-0.5.1.dist-info/licenses/LICENSE.txt
ssm_client/__init__.py
ssm_client/containers/__init__.py
ssm_client/containers/collection_container.py
ssm_client/containers/dataset_container.py
ssm_client/io/__init__.py
ssm_client/io/formats.py
ssm_client/io/jcamp.py
ssm_client/io/rruff.py
ssm_client/io/scidata_jsonld.py
ssm_client/io/ssm_json.py
ssm_client/services/__init__.py
ssm_client/services/collection_service.py
ssm_client/services/dataset_service.py
ssm_client/ssm_rester.py
ssm_client/version.py
ssm_client-0.5.1.dist-info/RECORD
