Metadata-Version: 2.1
Name: ssm-client
Version: 0.5.1
Summary: SSM Python Client
Author-Email: Marshall McDonnell <mcdonnellmt@ornl.gov>
License: BSD 3-Clause License
Requires-Python: <4.0,>=3.8.1
Requires-Dist: numpy<2.0.0,>=1.24.2
Requires-Dist: requests<3.0.0,>=2.28.2
Requires-Dist: toml<1.0.0,>=0.10.2
Requires-Dist: scidatalib==0.2.6a6
Requires-Dist: jupyter>=1.0.0; extra == "notebooks"
Requires-Dist: ruff>=0.6.1; extra == ":lint"
Provides-Extra: notebooks
Provides-Extra: :lint
